dbconnector.py
similarity.py
TelegramTopPost-0.0.1.dist-info/DESCRIPTION.rst
TelegramTopPost-0.0.1.dist-info/METADATA
TelegramTopPost-0.0.1.dist-info/RECORD
TelegramTopPost-0.0.1.dist-info/WHEEL
TelegramTopPost-0.0.1.dist-info/metadata.json
TelegramTopPost-0.0.1.dist-info/top_level.txt
